<?xml version="1.0" encoding="utf-8" ?>
<dwsync>
<file name="jquery-2.1.4.js" server="www.justinwintercg.com" local="130782824834317759" remote="130856257200000000" Dst="0" />
<file name="scripts.js" server="www.justinwintercg.com" local="130856248491013117" remote="130856257200000000" Dst="0" />
<file name="jquery-2.1.4.js" server="www.justinwintercg.com/completedev.justinwintercg.com/" local="130856257200000000" remote="130856257200000000" Dst="0" />
<file name="scripts.js" server="www.justinwintercg.com/completedev.justinwintercg.com/" local="130856257200000000" remote="130856257200000000" Dst="0" />
<file name="jquery-2.1.4.intellisense.js" server="www.justinwintercg.com/completedev.justinwintercg.com/" local="130959724350504823" remote="130856259000000000" Dst="0" />
<file name="jquery-2.1.4.min.js" server="www.justinwintercg.com/completedev.justinwintercg.com/" local="130959724352473016" remote="130856259000000000" Dst="0" />
<file name="jquery-2.1.4.min.map" server="www.justinwintercg.com/completedev.justinwintercg.com/" local="130959724355249841" remote="130856259000000000" Dst="0" />
<file name="jquery-2.1.4.js" server="ftp.wjwinter.com" local="130856257200000000" remote="130998181800000000" Dst="0" />
<file name="scripts.js" server="ftp.wjwinter.com" local="130856257200000000" remote="130998181800000000" Dst="0" />
<file name="jquery-2.1.4.min.js" server="ftp.wjwinter.com" local="130959724352473016" remote="130998181800000000" Dst="0" />
<file name="jquery-ui.min.js" server="ftp.wjwinter.com" local="130876924711707055" remote="130998181800000000" Dst="0" />
<file name="jquery-2.1.4.intellisense.js" server="ftp.wjwinter.com" local="130959724350504823" remote="130998181800000000" Dst="0" />
<file name="jquery-2.1.4.min.map" server="ftp.wjwinter.com" local="130959724355249841" remote="130998181800000000" Dst="0" />
<file name="jquery-ui-1.11.4.zip" server="ftp.wjwinter.com" local="130876923068832331" remote="130998181800000000" Dst="0" />
</dwsync>